priompt/__init__.py
priompt/components.py
priompt/lib.py
priompt/openai.py
priompt/output_catcher.py
priompt/preview.py
priompt/tokenizer.py
priompt/types.py
priompt-0.1.2.dist-info/METADATA
priompt-0.1.2.dist-info/WHEEL
priompt-0.1.2.dist-info/licenses/LICENSE.md
priompt-0.1.2.dist-info/RECORD
