Metadata-Version: 2.3
Name: priompt
Version: 0.1.2
Summary: Priompt (priority + prompt) is prompting library. It uses priorities to decide what to include in the context window.
Author-email: Cyrus Nouroozi <cyrus@zenbase.ai>
Requires-Python: >=3.8
Requires-Dist: beartype>=0.19.0
Requires-Dist: pyyaml>=6.0.2
Requires-Dist: tiktoken>=0.8.0
Requires-Dist: typing-extensions>=4.12.2
Requires-Dist: ujson>=5.10.0
